teg_regression.py
teg_regression-0.1.3.dist-info/LICENSE
teg_regression-0.1.3.dist-info/METADATA
teg_regression-0.1.3.dist-info/WHEEL
teg_regression-0.1.3.dist-info/top_level.txt
teg_regression-0.1.3.dist-info/RECORD
